hydra_plugins/jz_hydra_submitit_launcher/__init__.py
hydra_plugins/jz_hydra_submitit_launcher/resolvers.py
hydra_plugins/jz_hydra_submitit_launcher/searchpath_config.py
hydra_plugins/jz_hydra_submitit_launcher/bin/hydra-submitit-launch
hydra_plugins/jz_hydra_submitit_launcher/hydra/launcher/4gpus_dev.yaml
hydra_plugins/jz_hydra_submitit_launcher/hydra/launcher/4gpus_t3.yaml
hydra_plugins/jz_hydra_submitit_launcher/hydra/launcher/4gpus_t4.yaml
hydra_plugins/jz_hydra_submitit_launcher/hydra/launcher/base.yaml
hydra_plugins/jz_hydra_submitit_launcher/hydra/launcher/dev.yaml
hydra_plugins/jz_hydra_submitit_launcher/hydra/launcher/t3.yaml
hydra_plugins/jz_hydra_submitit_launcher/hydra/launcher/t4.yaml
jz_hydra_submitit_launcher-0.1.5.data/scripts/hydra-submitit-launch
jz_hydra_submitit_launcher-0.1.5.dist-info/LICENSE
jz_hydra_submitit_launcher-0.1.5.dist-info/METADATA
jz_hydra_submitit_launcher-0.1.5.dist-info/WHEEL
jz_hydra_submitit_launcher-0.1.5.dist-info/top_level.txt
jz_hydra_submitit_launcher-0.1.5.dist-info/RECORD
