Metadata-Version: 2.1
Name: jz-hydra-submitit-launcher
Version: 0.1.5
Summary: Jean Zay tailored Hydra submitit launcher.
Home-page: https://github.com/zaccharieramzi/jz-hydra-submitit-launcher
Author: Zaccharie Ramzi
Author-email: zaccharie.ramzi@gmail.com
License: MIT
Keywords: hydra,submitit,jean-zay
Classifier: Programming Language :: Python :: 3
Classifier: License :: OSI Approved :: MIT License
Classifier: Operating System :: OS Independent
Requires-Python: >=3.6
License-File: LICENSE
Requires-Dist: hydra-core
Requires-Dist: hydra-submitit-launcher
